ifq/__init__.py
ifq/__main__.py
ifq/cli.py
ifq-0.4.dist-info/LICENSE
ifq-0.4.dist-info/METADATA
ifq-0.4.dist-info/WHEEL
ifq-0.4.dist-info/entry_points.txt
ifq-0.4.dist-info/top_level.txt
ifq-0.4.dist-info/RECORD
