Metadata-Version: 2.1
Name: ifq
Version: 0.4
Summary: CLI tool and Python library to download PDF issues of ilfattoquotidiano.it
Author: Maurizio Branca
License: Apache-2.0
Project-URL: Homepage, https://github.com/zmoog/ifq
Project-URL: Changelog, https://github.com/zmoog/ifq/releases
Project-URL: Issues, https://github.com/zmoog/ifq/issues
Project-URL: CI, https://github.com/zmoog/ifq/actions
Classifier: License :: OSI Approved :: Apache Software License
Requires-Python: >=3.8
License-File: LICENSE
Requires-Dist: click
Requires-Dist: requests
Requires-Dist: lxml
Provides-Extra: test
Requires-Dist: pytest; extra == "test"
Requires-Dist: black; extra == "test"
Requires-Dist: flake8; extra == "test"
Requires-Dist: isort; extra == "test"
